README.md
setup.cfg
setup.py
amino.li.egg-info/PKG-INFO
amino.li.egg-info/SOURCES.txt
amino.li.egg-info/dependency_links.txt
amino.li.egg-info/requires.txt
amino.li.egg-info/top_level.txt
aminoli/__init__.py
aminoli/acm.py
aminoli/client.py
aminoli/socket.py
aminoli/sub_client.py
aminoli/asyncfix/__init__.py
aminoli/asyncfix/acm.py
aminoli/asyncfix/client.py
aminoli/asyncfix/socket.py
aminoli/asyncfix/sub_client.py
aminoli/lib/__init__.py
aminoli/lib/util/__init__.py
aminoli/lib/util/exceptions.py
aminoli/lib/util/headers.py
aminoli/lib/util/helpers.py
aminoli/lib/util/objects.py