Metadata-Version: 2.1
Name: amino.li
Version: 0.6
Summary: Library for Amino.
Home-page: https://github.com/LucasAlgerDay/amino.li
Author: Lucas
Author-email: lucasday173@gmail.com
License: MIT
Keywords: aminoapps,amino.li,amino,amino-bot,narvii,api,python,python3,python3.x
Requires-Python: >=3.6
